CEFR_Classifier_French/__init__.py
CEFR_Classifier_French/app.py
CEFR_Classifier_French/conf.py
CEFR_Classifier_French/utils.py
CEFR_Classifier_French/inference/__init__.py
CEFR_Classifier_French/inference/predict.py
CEFR_Classifier_French/pages/File_Inference.py
CEFR_Classifier_French/pages/Sentence_Inference.py
CEFR_Classifier_French/pages/Training.py
CEFR_Classifier_French/pages/__init__.py
CEFR_Classifier_French/train/__init__.py
CEFR_Classifier_French/train/trainer.py
CEFR_Classifier_French/train/utils.py
CEFR_Classifier_French-0.2.dist-info/METADATA
CEFR_Classifier_French-0.2.dist-info/WHEEL
CEFR_Classifier_French-0.2.dist-info/top_level.txt
CEFR_Classifier_French-0.2.dist-info/RECORD
